README.md
setup.py
vaw.py
vaw.egg-info/PKG-INFO
vaw.egg-info/SOURCES.txt
vaw.egg-info/dependency_links.txt
vaw.egg-info/requires.txt
vaw.egg-info/top_level.txt