Metadata-Version: 1.2
Name: vaw
Version: 1.3
Summary: This is a high-level wrapper for VK API
Home-page: https://github.com/mrbirdman2000/vaw
Author: mrbirdman2000
Author-email: kostya.kolesnyak@yandex.ru
License: GPL
Platform: any
Classifier: Development Status :: 3 - Alpha
Classifier: Programming Language :: Python :: 3.6
Classifier: Intended Audience :: Developers
Classifier: License :: OSI Approved :: GNU General Public License (GPL)
Classifier: Operating System :: OS Independent
Classifier: Topic :: Software Development :: Libraries :: Python Modules
Requires-Python: >=3.6
